preflight/__init__.py
python_preflight-0.1.dist-info/LICENSE
python_preflight-0.1.dist-info/WHEEL
python_preflight-0.1.dist-info/METADATA
python_preflight-0.1.dist-info/RECORD
